pyperclip/__init__.py
pyperclip_termux-0.0.2.dist-info/LICENSE
pyperclip_termux-0.0.2.dist-info/METADATA
pyperclip_termux-0.0.2.dist-info/WHEEL
pyperclip_termux-0.0.2.dist-info/top_level.txt
pyperclip_termux-0.0.2.dist-info/RECORD
